async_app/__about__.py
async_app/__init__.py
async_app/app.py
async_app/config.py
async_app/utils.py
async_app-1.0.0b30.dist-info/DESCRIPTION.rst
async_app-1.0.0b30.dist-info/METADATA
async_app-1.0.0b30.dist-info/RECORD
async_app-1.0.0b30.dist-info/WHEEL
async_app-1.0.0b30.dist-info/metadata.json
async_app-1.0.0b30.dist-info/top_level.txt
async_app-1.0.0b30.dist-info/zip-safe
