Metadata-Version: 2.0
Name: async-app
Version: 1.0.0b30
Summary: AsyncIO application as a hierarchy of services
Home-page: https://github.com/Kentzo/async_app/
Author: Ilya Kulakov
Author-email: kulakov.ilya@gmail.com
License: Apache 2
Keywords: asyncio,app,framework
Platform: UNKNOWN
Classifier: Development Status :: 4 - Beta
Classifier: Framework :: AsyncIO
Classifier: Intended Audience :: Developers
Classifier: Programming Language :: Python :: 3.6
Classifier: Topic :: Software Development :: Libraries :: Application Frameworks
Classifier: License :: OSI Approved :: Apache Software License
Requires-Python: >=3.6
Provides-Extra: pytypes
Requires-Dist: pytypes; extra == 'pytypes'
Provides-Extra: typeguard
Requires-Dist: typeguard; extra == 'typeguard'
